processtransformer/__init__.py
processtransformer/constants.py
processtransformer/data/__init__.py
processtransformer/data/loader.py
processtransformer/data/processor.py
processtransformer/models/__init__.py
processtransformer/models/transformer.py
processtransformer-0.1.3.dist-info/LICENSE.txt
processtransformer-0.1.3.dist-info/METADATA
processtransformer-0.1.3.dist-info/WHEEL
processtransformer-0.1.3.dist-info/top_level.txt
processtransformer-0.1.3.dist-info/RECORD
