Metadata-Version: 2.1
Name: processtransformer
Version: 0.1.3
Summary: Process Transformer Network for Predictive Business Process Monitoring Tasks
Home-page: https://github.com/Zaharah/processtransformer
Author: Zaharah Bukhsh
Author-email: z.bukhsh@tue.nl
License: Apache-2.0
Download-URL: https://pypi.org/project/processtransformer/
Keywords: Business Process Mointoring,Predictive Business Process,Transformer,Attention-Mechanism,Neural Network,Process Transformer
Platform: UNKNOWN
Requires-Dist: tensorflow (>=2.4)
Requires-Dist: numpy
Requires-Dist: scikit-learn
Requires-Dist: pandas
